LICENSE
MANIFEST.in
README.md
setup.cfg
setup.py
versioneer.py
ugali/__init__.py
ugali/_version.py
ugali.egg-info/PKG-INFO
ugali.egg-info/SOURCES.txt
ugali.egg-info/dependency_links.txt
ugali.egg-info/requires.txt
ugali.egg-info/top_level.txt
ugali/analysis/__init__.py
ugali/analysis/farm.py
ugali/analysis/imf.py
ugali/analysis/isochrone.py
ugali/analysis/kernel.py
ugali/analysis/loglike.py
ugali/analysis/mcmc.py
ugali/analysis/model.py
ugali/analysis/pipeline.py
ugali/analysis/prior.py
ugali/analysis/results.py
ugali/analysis/scan.py
ugali/analysis/search.py
ugali/analysis/source.py
ugali/candidate/__init__.py
ugali/candidate/associate.py
ugali/config/__init__.py
ugali/isochrone/__init__.py
ugali/isochrone/composite.py
ugali/isochrone/dartmouth.py
ugali/isochrone/empirical.py
ugali/isochrone/mesa.py
ugali/isochrone/model.py
ugali/isochrone/padova.py
ugali/isochrone/parsec.py
ugali/observation/__init__.py
ugali/observation/catalog.py
ugali/observation/mask.py
ugali/observation/roi.py
ugali/preprocess/__init__.py
ugali/preprocess/database.py
ugali/preprocess/dotter.py
ugali/preprocess/maglims.py
ugali/preprocess/mangle.py
ugali/preprocess/padova.py
ugali/preprocess/pixelize.py
ugali/simulation/__init__.py
ugali/simulation/analyzer.py
ugali/simulation/population.py
ugali/simulation/simulator.py
ugali/simulation/validation.py
ugali/utils/__init__.py
ugali/utils/batch.py
ugali/utils/bayesian_efficiency.py
ugali/utils/binning.py
ugali/utils/config.py
ugali/utils/constants.py
ugali/utils/factory.py
ugali/utils/fileio.py
ugali/utils/healpix.py
ugali/utils/idl.py
ugali/utils/logger.py
ugali/utils/mlab.py
ugali/utils/parabola.py
ugali/utils/parser.py
ugali/utils/plotting.py
ugali/utils/projector.py
ugali/utils/shell.py
ugali/utils/skymap.py
ugali/utils/speed.py
ugali/utils/stats.py