Metadata-Version: 1.1
Name: ugali
Version: 1.8.0
Summary: Ultra-faint galaxy likelihood toolkit.
Home-page: https://github.com/DarkEnergySurvey/ugali
Author: Keith Bechtol & Alex Drlica-Wagner
Author-email: bechtol@wisc.edu, kadrlica@fnal.gov
License: UNKNOWN
Platform: any
Classifier: Development Status :: 4 - Beta
Classifier: Intended Audience :: Science/Research
Classifier: Intended Audience :: Developers
Classifier: License :: OSI Approved :: MIT License
Classifier: Natural Language :: English
Classifier: Operating System :: MacOS :: MacOS X
Classifier: Operating System :: POSIX :: Linux
Classifier: Programming Language :: Python :: 2
Classifier: Programming Language :: Python :: 3
Classifier: Topic :: Scientific/Engineering
Classifier: Topic :: Scientific/Engineering :: Astronomy
Classifier: Topic :: Scientific/Engineering :: Physics
